[{"name":"Heihe","lat":50.24413,"lon":127.49016,"population":223832,"iso_a3":"CHN","country":"China","is_capital":false,"name_en":"Heihe","name_es":"Heihe","name_fr":"Heihe","name_it":"Heihe","name_ru":"Хэйхэ","elevation":139.0,"timezone":"Asia/Shanghai","admin1_name":"Heilongjiang"},{"name":"Blagoveshchensk","lat":50.27593,"lon":127.52637,"population":225091,"iso_a3":"RUS","country":"Russia","is_capital":false,"name_en":"Blagoveshchensk","name_es":"Blagovéshchensk","name_fr":"Blagovechtchensk","name_it":"Blagoveščensk","name_ru":"Благовещенск","elevation":133.0,"timezone":"Asia/Yakutsk","admin1_name":"Amur Oblast"}]