[{"name":"Dayton","lat":39.75895,"lon":-84.19161,"population":135512,"iso_a3":"USA","country":"United States","is_capital":false,"name_en":"Dayton","name_es":"Dayton","name_fr":"Dayton","name_it":"Dayton","name_ru":"Дейтон","elevation":237.0,"timezone":"America/New_York","admin1_name":"Ohio"},{"name":"Springfield","lat":39.92423,"lon":-83.80882,"population":59680,"iso_a3":"USA","country":"United States","is_capital":false,"name_en":"Springfield","name_es":"Springfield","name_fr":"Springfield","name_it":"Springfield","name_ru":"Спрингфилд","elevation":305.0,"timezone":"America/New_York","admin1_name":"Ohio"},{"name":"Kettering","lat":39.6895,"lon":-84.16883,"population":55525,"iso_a3":"USA","country":"United States","is_capital":false,"name_en":"Kettering","name_es":"Kettering","name_fr":"Kettering","name_it":"Kettering","name_ru":"Кеттеринг","elevation":307.0,"timezone":"America/New_York","admin1_name":"Ohio"},{"name":"Newark","lat":40.05812,"lon":-82.40126,"population":47986,"iso_a3":"USA","country":"United States","is_capital":false,"name_en":"Newark","name_es":"Newark","name_fr":"Newark","name_it":"Newark","name_ru":"Ньюарк","elevation":260.0,"timezone":"America/New_York","admin1_name":"Ohio"},{"name":"Mansfield","lat":40.75839,"lon":-82.51545,"population":46830,"iso_a3":"USA","country":"United States","is_capital":false,"name_en":"Mansfield","name_es":"Mansfield","name_fr":"Mansfield","name_it":"Mansfield","name_ru":"Мэнсфилд","elevation":382.0,"timezone":"America/New_York","admin1_name":"Ohio"},{"name":"Beavercreek","lat":39.70923,"lon":-84.06327,"population":46277,"iso_a3":"USA","country":"United States","is_capital":false,"name_en":"Beavercreek","name_es":"Beavercreek","name_fr":"Beavercreek","name_it":"Beavercreek","name_ru":"Beavercreek","elevation":267.0,"timezone":"America/New_York","admin1_name":"Ohio"},{"name":"Dublin","lat":40.09923,"lon":-83.11408,"population":45098,"iso_a3":"USA","country":"United States","is_capital":false,"name_en":"Dublin","name_es":"Dublin","name_fr":"Dublin","name_it":"Dublin","name_ru":"Дублин","elevation":253.0,"timezone":"America/New_York","admin1_name":"Ohio"},{"name":"Lancaster","lat":39.71368,"lon":-82.59933,"population":39766,"iso_a3":"USA","country":"United States","is_capital":false,"name_en":"Lancaster","name_es":"Lancaster","name_fr":"Lancaster","name_it":"Lancaster","name_ru":"Ланкастер","elevation":274.0,"timezone":"America/New_York","admin1_name":"Ohio"},{"name":"Grove City","lat":39.88145,"lon":-83.09296,"population":39388,"iso_a3":"USA","country":"United States","is_capital":false,"name_en":"Grove City","name_es":"Grove City","name_fr":"Grove City","name_it":"Grove City","name_ru":"Grove City","elevation":258.0,"timezone":"America/New_York","admin1_name":"Ohio"},{"name":"Westerville","lat":40.12617,"lon":-82.92907,"population":38384,"iso_a3":"USA","country":"United States","is_capital":false,"name_en":"Westerville","name_es":"Westerville","name_fr":"Westerville","name_it":"Westerville","name_ru":"Уэстервилл","elevation":262.0,"timezone":"America/New_York","admin1_name":"Ohio"},{"name":"Huber Heights","lat":39.84395,"lon":-84.12466,"population":38176,"iso_a3":"USA","country":"United States","is_capital":false,"name_en":"Huber Heights","name_es":"Huber Heights","name_fr":"Huber Heights","name_it":"Huber Heights","name_ru":"Huber Heights","elevation":284.0,"timezone":"America/New_York","admin1_name":"Ohio"},{"name":"Delaware","lat":40.29867,"lon":-83.06797,"population":37995,"iso_a3":"USA","country":"United States","is_capital":false,"name_en":"Delaware","name_es":"Delaware","name_fr":"Delaware","name_it":"Delaware","name_ru":"Делаварский","elevation":262.0,"timezone":"America/New_York","admin1_name":"Ohio"},{"name":"Lima","lat":40.74255,"lon":-84.10523,"population":37873,"iso_a3":"USA","country":"United States","is_capital":false,"name_en":"Lima","name_es":"Lima","name_fr":"Lima","name_it":"Lima","name_ru":"Лима","elevation":271.0,"timezone":"America/New_York","admin1_name":"Ohio"},{"name":"Reynoldsburg","lat":39.95479,"lon":-82.81212,"population":37158,"iso_a3":"USA","country":"United States","is_capital":false,"name_en":"Reynoldsburg","name_es":"Reynoldsburg","name_fr":"Reynoldsburg","name_it":"Reynoldsburg","name_ru":"Reynoldsburg","elevation":266.0,"timezone":"America/New_York","admin1_name":"Ohio"},{"name":"Marion","lat":40.58867,"lon":-83.12852,"population":36363,"iso_a3":"USA","country":"United States","is_capital":false,"name_en":"Marion","name_es":"Marion","name_fr":"Marion","name_it":"Marion","name_ru":"Мэрион","elevation":301.0,"timezone":"America/New_York","admin1_name":"Ohio"},{"name":"Upper Arlington","lat":39.99451,"lon":-83.06241,"population":34907,"iso_a3":"USA","country":"United States","is_capital":false,"name_en":"Upper Arlington","name_es":"Upper Arlington","name_fr":"Upper Arlington","name_it":"Upper Arlington","name_ru":"Upper Arlington","elevation":249.0,"timezone":"America/New_York","admin1_name":"Ohio"},{"name":"Gahanna","lat":40.01923,"lon":-82.87934,"population":34590,"iso_a3":"USA","country":"United States","is_capital":false,"name_en":"Gahanna","name_es":"Gahanna","name_fr":"Gahanna","name_it":"Gahanna","name_ru":"Gahanna","elevation":244.0,"timezone":"America/New_York","admin1_name":"Ohio"},{"name":"Hilliard","lat":40.0334,"lon":-83.15825,"population":33649,"iso_a3":"USA","country":"United States","is_capital":false,"name_en":"Hilliard","name_es":"Hilliard","name_fr":"Hilliard","name_it":"Hilliard","name_ru":"Hilliard","elevation":284.0,"timezone":"America/New_York","admin1_name":"Ohio"},{"name":"Fairborn","lat":39.82089,"lon":-84.01938,"population":33452,"iso_a3":"USA","country":"United States","is_capital":false,"name_en":"Fairborn","name_es":"Fairborn","name_fr":"Fairborn","name_it":"Fairborn","name_ru":"Fairborn","elevation":255.0,"timezone":"America/New_York","admin1_name":"Ohio"},{"name":"Mason","lat":39.36006,"lon":-84.30994,"population":32662,"iso_a3":"USA","country":"United States","is_capital":false,"name_en":"Mason","name_es":"Mason","name_fr":"Mason","name_it":"Mason","name_ru":"Мейсон","elevation":246.0,"timezone":"America/New_York","admin1_name":"Ohio"}]