[{"name":"San Carlos de Bariloche","lat":-41.14557,"lon":-71.30822,"population":95394,"iso_a3":"ARG","country":"Argentina","is_capital":false,"name_en":"Bariloche","name_es":"Bariloche","name_fr":"Bariloche","name_it":"Bariloche","name_ru":"Сан Карлос де Барилоче","elevation":839.0,"timezone":"America/Argentina/Salta","admin1_name":"Rio Negro"},{"name":"Puerto Montt","lat":-41.4693,"lon":-72.94237,"population":245902,"iso_a3":"CHL","country":"Chile","is_capital":false,"name_en":"Port Montt","name_es":"Puerto Montt","name_fr":"Puerto Montt","name_it":"Puerto Montt","name_ru":"Пуэрто-Монт","elevation":11.0,"timezone":"America/Santiago","admin1_name":"Los Lagos Region"},{"name":"Puerto Varas","lat":-41.31946,"lon":-72.98538,"population":37561,"iso_a3":"CHL","country":"Chile","is_capital":false,"name_en":"Puerto Varas","name_es":"Puerto Varas","name_fr":"Puerto Varas","name_it":"Puerto Varas","name_ru":"Пуэрто Варас","elevation":60.0,"timezone":"America/Santiago","admin1_name":"Los Lagos Region"}]