[{"name":"Djibo","lat":14.09864,"lon":-1.62665,"population":61462,"iso_a3":"BFA","country":"Burkina Faso","is_capital":false,"name_en":"Djibo","name_es":"Djibo","name_fr":"Djibo","name_it":"Djibo","name_ru":"Джибо","elevation":310.0,"timezone":"Africa/Ouagadougou","admin1_name":"Sahel"},{"name":"Dori","lat":14.03326,"lon":-0.03333,"population":46512,"iso_a3":"BFA","country":"Burkina Faso","is_capital":false,"name_en":"Dori","name_es":"Dori","name_fr":"Dori","name_it":"Dori","name_ru":"Дори","elevation":287.0,"timezone":"Africa/Ouagadougou","admin1_name":"Sahel"},{"name":"Aribinda","lat":14.22963,"lon":-0.86537,"population":45818,"iso_a3":"BFA","country":"Burkina Faso","is_capital":false,"name_en":"Aribinda","name_es":"Aribinda","name_fr":"Aribinda","name_it":"Aribinda","name_ru":"Aribinda","elevation":341.0,"timezone":"Africa/Ouagadougou","admin1_name":"Sahel"},{"name":"Gao","lat":16.27167,"lon":-0.04472,"population":133110,"iso_a3":"MLI","country":"Mali","is_capital":false,"name_en":"Gao","name_es":"Gao","name_fr":"Gao","name_it":"Gao","name_ru":"Гао","elevation":257.0,"timezone":"Africa/Bamako","admin1_name":"Gao"}]