[{"name":"Cazenga","lat":-8.82488,"lon":13.31318,"population":424528,"iso_a3":"AGO","country":"Angola","is_capital":false,"name_en":"Cazenga","name_es":"Cazenga","name_fr":"Cazenga","name_it":"Cazenga","name_ru":"Cazenga","elevation":77.0,"timezone":"Africa/Luanda","admin1_name":"Luanda"},{"name":"Porto Amboim","lat":-10.73251,"lon":13.76844,"population":91605,"iso_a3":"AGO","country":"Angola","is_capital":false,"name_en":"Porto Amboim","name_es":"Amboim","name_fr":"Porto Amboim","name_it":"Porto Amboim","name_ru":"Порту Амбоим","elevation":36.0,"timezone":"Africa/Luanda","admin1_name":"Kwanza Sul"},{"name":"Barra do Dande","lat":-8.47175,"lon":13.37011,"population":75000,"iso_a3":"AGO","country":"Angola","is_capital":false,"name_en":"Barra do Dande","name_es":"Barra do Dande","name_fr":"Barra do Dande","name_it":"Barra do Dande","name_ru":"Barra do Dande","elevation":10.0,"timezone":"Africa/Luanda","admin1_name":"Bengo"},{"name":"Gama","lat":-8.5675,"lon":13.47639,"population":66202,"iso_a3":"AGO","country":"Angola","is_capital":false,"name_en":"Gama","name_es":"Gama","name_fr":"Gama","name_it":"Gama","name_ru":"Gama","elevation":8.0,"timezone":"Africa/Luanda","admin1_name":"Bengo"},{"name":"Caxito","lat":-8.57848,"lon":13.66425,"population":55000,"iso_a3":"AGO","country":"Angola","is_capital":false,"name_en":"Caxito","name_es":"Caxito","name_fr":"Caxito","name_it":"Caxito","name_ru":"Кашито","elevation":20.0,"timezone":"Africa/Luanda","admin1_name":"Bengo"}]