[{"name":"Brno","lat":49.19522,"lon":16.60796,"population":379466,"iso_a3":"CZE","country":"Czechia","is_capital":false,"name_en":"Brno","name_es":"Brno","name_fr":"Brno","name_it":"Brno","name_ru":"Брно","elevation":226.0,"timezone":"Europe/Prague","admin1_name":"South Moravian"},{"name":"České Budějovice","lat":48.97447,"lon":14.47434,"population":93426,"iso_a3":"CZE","country":"Czechia","is_capital":false,"name_en":"České Budějovice","name_es":"České Budějovice","name_fr":"České Budějovice","name_it":"České Budějovice","name_ru":"Ческе-Будеёвице","elevation":390.0,"timezone":"Europe/Prague","admin1_name":"Jihočeský kraj"},{"name":"Hradec Králové","lat":50.20923,"lon":15.83277,"population":90596,"iso_a3":"CZE","country":"Czechia","is_capital":false,"name_en":"Hradec Králové","name_es":"Hradec Králové","name_fr":"Hradec Králové","name_it":"Hradec Králové","name_ru":"Градец Кралове","elevation":250.0,"timezone":"Europe/Prague","admin1_name":"Královéhradecký kraj"},{"name":"Pardubice","lat":50.04075,"lon":15.77659,"population":88520,"iso_a3":"CZE","country":"Czechia","is_capital":false,"name_en":"Pardubice","name_es":"Pardubice","name_fr":"Pardubice","name_it":"Pardubice","name_ru":"Пардубице","elevation":227.0,"timezone":"Europe/Prague","admin1_name":"Pardubický"},{"name":"Kladno","lat":50.14734,"lon":14.10285,"population":69664,"iso_a3":"CZE","country":"Czechia","is_capital":false,"name_en":"Kladno","name_es":"Kladno","name_fr":"Kladno","name_it":"Kladno","name_ru":"Кладно","elevation":390.0,"timezone":"Europe/Prague","admin1_name":"Central Bohemia"},{"name":"Stodůlky","lat":50.05,"lon":14.31667,"population":60758,"iso_a3":"CZE","country":"Czechia","is_capital":false,"name_en":"Stodůlky","name_es":"Stodůlky","name_fr":"Stodůlky","name_it":"Stodůlky","name_ru":"Stodůlky","elevation":342.0,"timezone":"Europe/Prague","admin1_name":"Prague"},{"name":"Jihlava","lat":49.3961,"lon":15.59124,"population":50108,"iso_a3":"CZE","country":"Czechia","is_capital":false,"name_en":"Jihlava","name_es":"Jihlava","name_fr":"Jihlava","name_it":"Jihlava","name_ru":"Йиглава","elevation":523.0,"timezone":"Europe/Prague","admin1_name":"Vysočina"},{"name":"Jablonec nad Nisou","lat":50.72431,"lon":15.17108,"population":46209,"iso_a3":"CZE","country":"Czechia","is_capital":false,"name_en":"Jablonec nad Nisou","name_es":"Jablonec nad Nisou","name_fr":"Jablonec nad Nisou","name_it":"Jablonec nad Nisou","name_ru":"Яблонец","elevation":518.0,"timezone":"Europe/Prague","admin1_name":"Liberecký kraj"},{"name":"Mladá Boleslav","lat":50.41135,"lon":14.90318,"population":43684,"iso_a3":"CZE","country":"Czechia","is_capital":false,"name_en":"Mladá Boleslav","name_es":"Mladá Boleslav","name_fr":"Mladá Boleslav","name_it":"Mladá Boleslav","name_ru":"Млада-Болеслав","elevation":241.0,"timezone":"Europe/Prague","admin1_name":"Central Bohemia"},{"name":"Česká Lípa","lat":50.68551,"lon":14.53764,"population":36815,"iso_a3":"CZE","country":"Czechia","is_capital":false,"name_en":"Česká Lípa","name_es":"Česká Lípa","name_fr":"Česká Lípa","name_it":"Česká Lípa","name_ru":"Ческа-Липа","elevation":263.0,"timezone":"Europe/Prague","admin1_name":"Liberecký kraj"},{"name":"Tábor","lat":49.41441,"lon":14.6578,"population":36264,"iso_a3":"CZE","country":"Czechia","is_capital":false,"name_en":"Tábor","name_es":"Tábor","name_fr":"Tábor","name_it":"Tábor","name_ru":"Табор","elevation":456.0,"timezone":"Europe/Prague","admin1_name":"Jihočeský kraj"},{"name":"Třebíč","lat":49.21492,"lon":15.88166,"population":34530,"iso_a3":"CZE","country":"Czechia","is_capital":false,"name_en":"Třebíč","name_es":"Třebíč","name_fr":"Třebíč","name_it":"Třebíč","name_ru":"Тршебич","elevation":405.0,"timezone":"Europe/Prague","admin1_name":"Vysočina"},{"name":"Kolín","lat":50.02806,"lon":15.1998,"population":33444,"iso_a3":"CZE","country":"Czechia","is_capital":false,"name_en":"Kolín","name_es":"Kolín","name_fr":"Kolín","name_it":"Kolín","name_ru":"Колин","elevation":215.0,"timezone":"Europe/Prague","admin1_name":"Central Bohemia"},{"name":"Trutnov","lat":50.56101,"lon":15.9127,"population":31398,"iso_a3":"CZE","country":"Czechia","is_capital":false,"name_en":"Trutnov","name_es":"Trutnov","name_fr":"Trutnov","name_it":"Trutnov","name_ru":"Трутнов","elevation":431.0,"timezone":"Europe/Prague","admin1_name":"Královéhradecký kraj"},{"name":"Dzierżoniów","lat":50.7282,"lon":16.65141,"population":34168,"iso_a3":"POL","country":"Poland","is_capital":false,"name_en":"Dzierżoniów","name_es":"Dzierżoniów","name_fr":"Dzierżoniów","name_it":"Dzierżoniów","name_ru":"Дзержонюв","elevation":278.0,"timezone":"Europe/Warsaw","admin1_name":"Lower Silesia"}]